pyuhand/__init__.py
pyuhand/motion.py
pyuhand/uhand.py
pyuhand-0.0.1.dist-info/LICENSE
pyuhand-0.0.1.dist-info/METADATA
pyuhand-0.0.1.dist-info/WHEEL
pyuhand-0.0.1.dist-info/top_level.txt
pyuhand-0.0.1.dist-info/RECORD
