Metadata-Version: 2.1
Name: pyuhand
Version: 0.0.1
Summary: A small library to use uhand2 in python
Home-page: https://github.com/peteh/pyuhand
Author: Pete
Author-email: github@kthxbye.us
License: UNKNOWN
Project-URL: Bug Tracker, https://github.com/peteh/pyuhand/issues
Platform: UNKNOWN
Classifier: Programming Language :: Python :: 3
Classifier: License :: OSI Approved :: GNU Lesser General Public License v3 (LGPLv3)
Classifier: Operating System :: OS Independent
Requires-Python: >=3.6
